simple_cicd/__init__.py
simple_cicd/ci_files.py
simple_cicd/functions.py
simple_cicd/script_parsing.py
simple_cicd/simple_cicd.py
simple_cicd-0.1.0.dist-info/LICENSE
simple_cicd-0.1.0.dist-info/METADATA
simple_cicd-0.1.0.dist-info/WHEEL
simple_cicd-0.1.0.dist-info/entry_points.txt
simple_cicd-0.1.0.dist-info/top_level.txt
simple_cicd-0.1.0.dist-info/RECORD
